st_on_machine_data/__init__.py
st_on_machine_data/frontend/build/asset-manifest.json
st_on_machine_data/frontend/build/bootstrap.min.css
st_on_machine_data/frontend/build/index.html
st_on_machine_data/frontend/build/precache-manifest.81bc9bb021f5d89c3dd2c8b06828d914.js
st_on_machine_data/frontend/build/service-worker.js
st_on_machine_data/frontend/build/static/css/main.5d85bd15.chunk.css
st_on_machine_data/frontend/build/static/css/main.5d85bd15.chunk.css.map
st_on_machine_data/frontend/build/static/js/2.52ba85b9.chunk.js
st_on_machine_data/frontend/build/static/js/2.52ba85b9.chunk.js.LICENSE.txt
st_on_machine_data/frontend/build/static/js/2.52ba85b9.chunk.js.map
st_on_machine_data/frontend/build/static/js/main.7ce2f887.chunk.js
st_on_machine_data/frontend/build/static/js/main.7ce2f887.chunk.js.map
st_on_machine_data/frontend/build/static/js/runtime-main.44d30fc2.js
st_on_machine_data/frontend/build/static/js/runtime-main.44d30fc2.js.map
streamlit_on_machine_data-8.0.3.dist-info/LICENSE
streamlit_on_machine_data-8.0.3.dist-info/METADATA
streamlit_on_machine_data-8.0.3.dist-info/WHEEL
streamlit_on_machine_data-8.0.3.dist-info/top_level.txt
streamlit_on_machine_data-8.0.3.dist-info/RECORD
