Metadata-Version: 2.1
Name: streamlit-on-machine-data
Version: 8.0.3
Home-page: 
Author: venrup
Author-email: development@venrup.com
Requires-Python: >=3.6
License-File: LICENSE
Requires-Dist: streamlit (>=0.63)
